{
  "acceptance_criteria": "Akseptkriterier:",
  "add_comment": "Legg til en kommentar",
  "add_issue": "Legg til avvik",
  "an_error_occurred": "Det skjedde en feil",
  "camera": "Kamera",
  "change_organization": "Endre organisasjon",
  "checks": "{} sjekker",
  "choose_organization": "Velg en organisasjon",
  "comment": "kommentar",
  "completed": "Fullført",
  "construction": "Konstruksjon",
  "continue_test": "Fortsett testen",
  "contract": "Kontrakt",
  "could_not_reach_the_server": "Klarte ikke å nå serveren",
  "create_new": "Lag ny",
  "deadline": "Tidsfrist",
  "description": "Beskrivelse",
  "discipline": "Disiplin",
  "done": "ferdig",
  "due_date_arg": "Due: {}",
  "edit": "rediger",
  "email": "E-post",
  "email_address": "E-postadresse",
  "fail": "Feilet",
  "finish": "ferdig",
  "go_back": "Gå tilbake",
  "hello": "hello",
  "image_library": "Bildebiliotek",
  "improvement": "Forbedring",
  "in_progress": "Pågår",
  "issues": "Avvik",
  "location": "Plassering",
  "login": "Logg inn",
  "logout": "Logg ut",
  "main_process": "Hovedprossess",
  "make_sure_you_give_the_issue_a_title": "Sørg for å gi avviket en tittel",
  "mark_as_done": "Marker som ferdig",
  "meta_data": "Metadata",
  "name": "Name",
  "new": "Ny",
  "no_organization_found": "Ingen organisasjon funnet",
  "object": "Objekt",
  "object_under_test": "Objekt som testes",
  "pass": "Godkjent",
  "password": "Passord",
  "photos": "Bilder",
  "present_completed": "{}% fullført",
  "required_field": "{} er påkrevd",
  "responsible": "Ansvarlig",
  "responsible_arg": "Ansvarlig: {}",
  "room": "Rom",
  "save": "Lagre",
  "select_a_test": "Velg en test",
  "select_project": "Velg prosjekt",
  "set_in_progress": "Marker som påbegynt",
  "start_time": "Start tid",
  "status": "Status",
  "submit_test": "Send inn test",
  "system_test_types": "Systemtesttyper",
  "systematic_completion": "Systematisk ferdigstillelse",
  "test_execution": "Testutførelse",
  "test_type": "Test type",
  "test_types": "Testtyper",
  "tests": "Tester",
  "title": "Tittel",
  "try_again": "Prøv på nytt",
  "type": "Type",
  "unknown_error": "Ukjent feil",
  "untested": "Utestet",
  "view_test_details": "Se testdetaljer",
  "view_test_report": "Vis testrapport"
}